ChIP_R-1.2.0.data/scripts/chipr
chipr/__init__.py
chipr/__main__.py
chipr/bed.py
chipr/chipr.py
chipr/ival.py
chipr/multipletesting.py
chipr/petprocessing.py
chipr/rankprod.py
chipr/tests.py
ChIP_R-1.2.0.dist-info/LICENSE
ChIP_R-1.2.0.dist-info/METADATA
ChIP_R-1.2.0.dist-info/WHEEL
ChIP_R-1.2.0.dist-info/entry_points.txt
ChIP_R-1.2.0.dist-info/top_level.txt
ChIP_R-1.2.0.dist-info/RECORD
