Metadata-Version: 2.1
Name: ChIP-R
Version: 1.2.0
Summary: ChIP-R is a method for assessing the reproducibility of replicated ChIP-seq type experiments. It incorporates the rank product method, a novel thresholding methods, and the use of peak fragmentation return the most reproducible peaks.
Home-page: https://github.com/rhysnewell/ChIP-R
Author: Rhys Newell, Mikael Boden, Alex Essebier
Author-email: r.newell@uq.edu.au
License: GPL-3.0
Keywords: ChIP-R
Platform: UNKNOWN
Classifier: Programming Language :: Python :: 3
Classifier: Development Status :: 5 - Production/Stable
Classifier: Topic :: Scientific/Engineering :: Bio-Informatics
Classifier: License :: OSI Approved :: GNU General Public License v3 or later (GPLv3+)
Requires-Python: >=3
Requires-Dist: scipy
Requires-Dist: numpy
